[
  {
    "id": "tax_deung_1",
    "no": 1,
    "sector": "등록면허세",
    "내용": "1. 「지방세법」상 등록면허세가 과세되는 등록 또는 등기가 아닌 것은? (단, 2026년 1월 1일 이후 등록 또는 등기한 것으로 가정함)",
    "옵션": [
      { "no": 1, "text": "광업권·어업권 및 양식업권의 취득에 따른 등록" },
      { "no": 2, "text": "외국인 소유의 선박을 직접 사용하기 위하여 연부취득 조건으로 수입하는 선박의 등록" },
      { "no": 3, "text": "취득세 부과제척기간이 경과한 주택의 등기" },
      { "no": 4, "text": "취득가액이 50만원 이하인 차량의 등록" },
      { "no": 5, "text": "사실상의 잔금지급일을 2025년 12월 1일로 하는 부동산(취득가액 1억원)의 소유권이전등기" }
    ],
    "answer": 5,
    "해설": "5번의 경우 취득세 과세대상인 일반적인 유상 부동산 취득에 따른 소유권이전등기이므로 취득세를 납부해야 하며, 등록면허세 과세대상 등기·등록에서 제외됩니다[cite: 858, 860]."
  },
  {
    "id": "tax_deung_2",
    "no": 2,
    "sector": "등록면허세",
    "내용": "2. 「지방세법」상 부동산등기에 대한 등록면허세의 과세표준과 표준세율로 틀린 것은?",
    "옵션": [
      { "no": 1, "text": "전세권 설정등기 : 전세금액의 1천분의 2" },
      { "no": 2, "text": "상속으로 인한 소유권 이전등기 : 부동산가액의 1천분의 8" },
      { "no": 3, "text": "지역권 설정 및 이전등기 : 요역지 가액의 1천분의 2" },
      { "no": 4, "text": "임차권 설정 및 이전등기 : 임차보증금의 1천분의 2" },
      { "no": 5, "text": "저당권 설정 및 이전등기 : 채권금액의 1천분의 2" }
    ],
    "answer": 4,
    "해설": "임차권 설정 및 이전등기의 등록면허세 과세표준은 '임차보증금'이 아니라 '월임대차금액'의 1천분의 2입니다[cite: 872, 875]."
  },
  {
    "id": "tax_deung_3",
    "no": 3,
    "sector": "등록면허세",
    "내용": "3. 「지방세법」상 등록면허세에 관한 설명으로 옳은 것은?",
    "옵션": [
      { "no": 1, "text": "부동산 등기에 대한 등록면허세 납세지는 부동산 소유자의 주소지이다." },
      { "no": 2, "text": "등록을 하려는 자가 신고의무를 다하지 않은 경우 등록면허세 산출세액을 등록하기 전까지 납부하였을 때에는 신고·납부한 것으로 보지만 무신고 가산세가 부과된다." },
      { "no": 3, "text": "상속으로 인한 소유권 이전 등기의 세율은 부동산 가액의 1천분의 15로 한다." },
      { "no": 4, "text": "부동산을 등기하려는 자는 과세표준에 세율을 적용하여 산출한 세액을 등기를 하기 전까지 납세지를 관할하는 지방자치단체의 장에게 신고·납부하여야 한다." },
      { "no": 5, "text": "대도시 밖에 있는 법인의 본점이나 주사무소를 대도시로 전입함에 따른 등기는 법인등기에 대한 세율의 100분의 200을 적용한다." }
    ],
    "answer": 4,
    "해설": "• 4번이 옳은 지문으로 정답입니다 [cite: 884].\n• 1번: 부동산 등기의 납세지는 부동산 소재지입니다 [cite: 887].\n• 2번: 신고를 안 했어도 등록 전까지 납부하면 신고하고 납부한 것으로 보아 가산세를 부과하지 않습니다 [cite: 888, 889].\n• 3번: 상속 이전등기 세율은 1천분의 8입니다 [cite: 890].\n• 5번: 대도시 전입 등기는 법인등기 표준세율의 100분의 300을 적용하여 중과세합니다[cite: 891]."
  },
  {
    "id": "tax_deung_4",
    "no": 4,
    "sector": "등록면허세",
    "내용": "4. 甲이 乙소유 부동산에 관해 전세권설정등기를 하는 경우 「지방세법」상 등록에 대한 등록면허세에 관한 설명으로 틀린 것은?",
    "옵션": [
      { "no": 1, "text": "등록면허세의 납세의무자는 전세권자인 甲이다." },
      { "no": 2, "text": "부동산 소재지와 乙의 주소지가 다른 경우 등록면허세의 납세지는 乙의 주소지로 한다." },
      { "no": 3, "text": "전세권설정등기에 대한 등록면허세의 표준세율은 전세 금액의 1,000분의 2이다." },
      { "no": 4, "text": "전세권설정등기에 대한 등록면허세의 산출세액이 건당 6천원보다 적을 때에는 등록면허세의 세액은 6천원으로 한다." },
      { "no": 5, "text": "만약 丙이 甲으로부터 전세권을 이전받아 등기하는 경우라면 등록면허세의 납세의무자는 丙이다." }
    ],
    "answer": 2,
    "해설": "부동산 등기에 대한 등록면허세 납세지는 주소지가 아니라 항상 '부동산 소재지'가 기준입니다[cite: 903]."
  },
  {
    "id": "tax_deung_5",
    "no": 5,
    "sector": "등록면허세",
    "내용": "5. 거주자인 개인 乙은 甲이 소유한 부동산(시가 6억원)에 전세기간 2년, 전세보증금 3억원으로 하는 전세계약을 체결하고, 전세권 설정등기를 하였다. 지방세법상 등록면허세에 관한 설명으로 옳은 것은?",
    "옵션": [
      { "no": 1, "text": "과세표준은 6억원이다." },
      { "no": 2, "text": "표준세율은 전세보증금의 1천분의 8이다." },
      { "no": 3, "text": "납부세액은 6천원이다." },
      { "no": 4, "text": "납세의무자는 乙이다." },
      { "no": 5, "text": "납세지는 甲의 주소지이다." }
    ],
    "answer": 4,
    "해설": "• 4번이 옳은 지문으로 정답입니다. 전세권 설정등기의 납세의무자는 전세권자인 乙이 됩니다 [cite: 916].\n• 1번: 과세표준은 전세금액인 3억원입니다 [cite: 913].\n• 2번: 표준세율은 전세금액의 1천분의 2입니다 [cite: 914].\n• 3번: 납부세액은 3억원 × 0.2% = 60만원입니다 [cite: 915].\n• 5번: 납세지는 부동산 소재지입니다[cite: 917]."
  },
  {
    "id": "tax_deung_6",
    "no": 6,
    "sector": "등록면허세",
    "내용": "6. 「지방세법」상 등록면허세에 관한 설명으로 틀린 것은?",
    "옵션": [
      { "no": 1, "text": "부동산 등기에 대한 등록면허세의 납세지는 부동산 소재지이다." },
      { "no": 2, "text": "등록을 하려는 자가 법정신고기한까지 등록면허세 산출세액을 신고하지 않은 경우로서 등록 전까지 그 산출세액을 납부한 때에도 「지방세기본법」에 따른 무신고가산세가 부과된다." },
      { "no": 3, "text": "등기 담당 공무원의 착오로 인한 지번의 오기에 대한 경정 등기에 대해서는 등록면허세를 부과하지 아니한다." },
      { "no": 4, "text": "채권금액으로 과세액을 정하는 경우에 일정한 채권금액이 없을 때에는 채권의 목적의 가액 또는 처분의 제한의 목적이 된 금액을 그 채권금액으로 본다." },
      { "no": 5, "text": "「한국은행법」 및 「한국수출입은행법」에 따른 은행업을 영위하기 위하여 대도시에서 법인을 설립함에 따른 등기를 한 법인이 그 등기일부터 2년 이내에 업종변경이나 업종 추가가 없는 때에는 등록면허세의 세율을 중과하지 아니한다." }
    ],
    "answer": 2,
    "해설": "등록면허세 납세의무자가 비록 신고는 안 했어도 등록을 하기 전까지 산출세액을 전액 납부했다면 정상적으로 신고하고 납부한 것으로 간주하여 무신고가산세를 일절 부과하지 않습니다[cite: 934, 935]."
  },
  {
    "id": "tax_deung_7",
    "no": 7,
    "sector": "등록면허세",
    "내용": "7. 「지방세법」상 등록면허세에 관한 설명으로 옳은 것은?",
    "옵션": [
      { "no": 1, "text": "지방자치단체의 장은 등록면허세의 세율을 표준세율의 100분의 60의 범위에서 가감할 수 있다." },
      { "no": 2, "text": "등록 당시에 감가상각의 사유로 가액이 달라진 경우 그 가액에 대한 증명여부에 관계없이 변경전 가액을 과세표준으로 한다." },
      { "no": 3, "text": "부동산 등록에 대한 신고가 없는 경우 취득 당시 시가표준액의 100분의 110을 과세표준으로 한다." },
      { "no": 4, "text": "지목이 묘지인 토지의 등록에 대하여는 등록면허세를 부과한다." },
      { "no": 5, "text": "부동산 등기에 대한 등록면허세의 납세지는 부동산 소재지로 하며, 납세지가 분명하지 아니한 경우에는 등록관청 소재지로 한다." }
    ],
    "answer": 5,
    "해설": "• 5번이 옳은 지문으로 정답입니다 [cite: 943].\n• 1번: 세율 가감 범위는 100분의 50 범위입니다 [cite: 945].\n• 2번: 감가상각이나 자산재평가 등으로 등록 당시 가액이 달라지면 법인장부나 결산서 등으로 증명되는 '변경된 가액'을 과세표준으로 삼습니다 [cite: 946].\n• 3번: 신고가 없을 시에는 등록 당시의 시가표준액 그대로가 과세표준이 됩니다 [cite: 947].\n• 4번: 지목이 묘지인 토지의 등기는 등록면허세 비과세 대상입니다[cite: 948]."
  },
  {
    "id": "tax_deung_8",
    "no": 8,
    "sector": "등록면허세",
    "내용": "8. 지방세법령상 등록에 대한 등록면허세가 비과세되는 경우로 틀린 것은?",
    "옵션": [
      { "no": 1, "text": "지방자치단체조합이 자기를 위하여 받는 등록" },
      { "no": 2, "text": "무덤과 이에 접속된 부속시설물의 부지로 사용되는 토지로서 지적공부상 지목이 묘지인 토지에 관한 등기" },
      { "no": 3, "text": "「채무자 회생 및 파산에 관한 법률」상 법원 사무관 등의 촉탁이나 등기소의 직권에 의한 등기·등록" },
      { "no": 4, "text": "대한민국 정부기관의 등록에 대하여 과세하는 외국정부의 등록" },
      { "no": 5, "text": "등기 담당 공무원의 착오로 인한 주소 등의 단순한 표시변경 등기" }
    ],
    "answer": 4,
    "해설": "대한민국 정부기관의 등록에 과세하는 외국정부의 등록은 상호주의 원칙에 따라 우리나라도 비과세 혜택을 주지 않고 똑같이 등록면허세를 정상 '과세'합니다[cite: 960]."
  },
  {
    "id": "tax_deung_9",
    "no": 9,
    "sector": "등록면허세",
    "내용": "9. 지방세법령상 등록에 대한 등록면허세에 관한 설명으로 틀린 것은?",
    "옵션": [
      { "no": 1, "text": "같은 등록에 관계되는 재산이 둘 이상의 지방자치단체에 걸쳐 있어 등록면허세를 지방자치단체별로 부과할 수 없을 때에는 등록관청 소재지를 납세지로 한다." },
      { "no": 2, "text": "지방자치단체의 장은 조례로 정하는 바에 따라 등록면허세의 세율을 부동산 등기에 따른 표준세율의 100분의 50의 범위에서 가감할 수 " },
      { "no": 3, "text": "주택의 토지와 건축물을 한꺼번에 평가하여 토지나 건축물에 대한 과세표준이 구분되지 아니하는 경우에는 한꺼번에 평가한 개별주택가격을 토지나 건축물의 가액 비율로 나눈 금액을 각각 토지와 건축물의 과세표준으로 한다." },
      { "no": 4, "text": "부동산의 등록에 대한 등록면허세의 과세표준은 등록자가 신고한 당시의 가액으로 하고, 신고가 없거나 신고가액이 시가표준액보다 많은 경우에는 시가표준액으로 한다." },
      { "no": 5, "text": "채권자대위자는 납세의무자를 대위하여 부동산의 등기에 대한 등록면허세를 신고납부할 수 있다." }
    ],
    "answer": 4,
    "해설": "등록면허세의 과세표준은 등록 당시 신고가액이 원칙이지만, 신고가 없거나 신고가액이 시가표준액보다 '적은' 경우에 한하여 시가표준액을 적용합니다. 시가표준액보다 '많은' 경우에는 신고가액 그대로가 과세표준이 됩니다[cite: 969]."
  },
  {
    "id": "tax_deung_10",
    "no": 10,
    "sector": "등록면허세",
    "내용": "10. 「지방세법상 취득세 및 등록면허세에 관한 설명으로 옳은 것은?",
    "옵션": [
      { "no": 1, "text": "취득세 과세물건을 취득한 후 중과세 세율 적용대상이 되었을 경우 30일 이내에 산출세액에서 이미 납부한 세액(가산세 포함)을 공제하여 신고·납부하여야 한다." },
      { "no": 2, "text": "취득세 과세물건을 취득한 자가 재산권의 취득에 관한 사항을 등기하는 경우 등기한 후 60일 내에 취득세를 신고·납부하여야 한다." },
      { "no": 3, "text": "지방자치단체의 장은 특수관계인간의 거래로 그 취득에 대한 조세부담을 부당하게 감소시키는 행위 또는 계산을 한 것으로 인정되는 경우에는 유상승계취득의 경우에 사실상취득가격을 취득당시 가액으로 결정할 수 " },
      { "no": 4, "text": "부동산가압류에 대한 등록면허세의 세율은 부동산가액의 1천분의 2로 한다." },
      { "no": 5, "text": "등록하려는 자가 신고의무를 다하지 아니하고 등록면허세 산출세액을 등록하기 전까지 납부하였을 때에는 신고·납부한 것으로 본다." }
    ],
    "answer": 5,
    "해설": "• 5번이 옳은 지문으로 정답입니다 [cite: 983].\n• 1번: 중과세 대상이 된 날로부터 60일 이내에 이미 납부한 세액(가산세 제외)을 공제하고 신고·납부해야 합니다 [cite: 985].\n• 2번: 재산권을 등기·등록하려는 경우에는 기한 내라 할지라도 무조건 '등기하기 전까지' 취득세를 신고·납부해야 합니다 [cite: 986].\n• 3번: 특수관계인 간의 부당행위계산에 해당하면 사실상취득가격 규정에도 불구하고 '시가인정액'을 기준으로 과세표준을 과세관청이 재결정합니다 [cite: 987].\n• 4번: 부동산 가압류에 대한 등록면허세 과세표준은 부동산가액이 아니라 '채권금액'의 1천분의 2입니다[cite: 988]."
  }
]