[
  {
    "id": "tax_so_1",
    "no": 1,
    "sector": "소득세",
    "내용": "1. 「소득세법」상 거주자의 부동산임대업에서 발생하는 소득에 관한 설명으로 옳은 것은?",
    "옵션": [
      { "no": 1, "text": "공익사업과 관련한 지역권을 대여함으로써 발생하는 소득은 사업소득이다." },
      { "no": 2, "text": "공익사업과 관련한 지상권을 대여함으로써 발생하는 소득은 사업소득이다." },
      { "no": 3, "text": "미등기부동산을 임대하고 그 대가로 받는 것은 사업소득이 아니다." },
      { "no": 4, "text": "자기소유의 부동산을 타인의 담보로 사용하게 하고 그 사용대가로 받는 것은 사업소득이다." },
      { "no": 5, "text": "국외소재 주택을 임대하고 그 대가로 받는 것은 사업소득이 아니다." }
    ],
    "answer": 4,
    "해설": "• 4번이 옳은 지문으로 정답입니다. 자기 소유 부동산을 타인의 채무 담보로 제공하고 받는 대가는 부동산임대업의 사업소득으로 과세합니다.\n• 1번, 2번: 공익사업과 관련된 지역권·지상권 대여 소득은 사업소득이 아니라 '기타소득'입니다.\n• 3번: 세법은 실질과세원칙에 따르므로 미등기 부동산 임대 대가도 정상 사업소득에 해당합니다.\n• 5번: 국외소재 주택임대소득은 주택 수와 무조건 관계없이 국내에서 사업소득으로 과세합니다."
  },
  {
    "id": "tax_so_2",
    "no": 2,
    "sector": "소득세",
    "내용": "2. 「소득세법」상 거주자의 부동산 임대와 관련하여 발생한 소득에 관한 설명으로 틀린 것은?",
    "옵션": [
      { "no": 1, "text": "국외에 소재하는 주택임대소득은 주택 수에 관계없이 과세된다." },
      { "no": 2, "text": "3주택(소형주택 아님)을 소유하는 자가 받은 보증금의 합계액이 2억원인 경우 법령으로 정하는 바에 따라 계산한 간주임대료를 사업소득 총수입금액에 산입한다." },
      { "no": 3, "text": "2주택(고가주택 및 소형주택 아님)과 2개의 상업용 건물을 소유하는 자가 보증금을 받은 경우 2개의 상업용 건물에 대하여만 법령으로 정하는 바에 따라 계산한 간주임대료를 사업소득 총수입금액에 산입한다." },
      { "no": 4, "text": "주택임대소득이 과세되는 고가주택은 과세기간 종료일 현재 기준시가가 12억원을 초과하는 주택을 말한다." },
      { "no": 5, "text": "사업자가 부동산을 임대하고 임대료 외에 전기료·수도료 등 공공요금의 명목으로 지급받은 금액이 공공요금의 납부액을 초과할 때 그 초과하는 금액은 사업소득 총수입금액에 산입한다." }
    ],
    "answer": 2,
    "해설": "주택에 대한 전세보증금 간주임대료는 '3주택 이상' 소유자이면서 보증금 합계액이 '3억원을 초과'하는 경우에만 과세하므로, 보증금 합계가 2억원인 경우에는 간주임대료를 계산하지 않습니다."
  },
  {
    "id": "tax_so_3",
    "no": 3,
    "sector": "소득세",
    "내용": "3. 「소득세법」상 거주자가 국내소재 부동산 등을 임대하여 발생하는 소득에 관한 설명으로 틀린 것은?",
    "옵션": [
      { "no": 1, "text": "공익사업과 관련한 지상권의 대여로 인한 소득은 부동산임대업에서 발생한 소득에서 제외한다." },
      { "no": 2, "text": "부동산임대업에서 발생한 소득은 사업소득에 해당한다." },
      { "no": 3, "text": "주거용 건물 임대업에서 발생한 결손금은 종합소득 과세표준을 계산할 때 공제한다." },
      { "no": 4, "text": "부부가 각각 주택을 1채씩 보유한 상태에서 그 중 1주택을 임대하고 연간 1,800만원의 임대료를 받았을 경우 주택임대에 따른 과세소득은 분리과세와 종합과세를 선택할 수 있다." },
      { "no": 5, "text": "임대보증금의 간주임대료를 계산하는 과정에서 금융수익을 차감할 때 그 금융수익은 수입이자와 할인료, 수입배당금, 유가증권처분이익으로 한다." }
    ],
    "answer": 5,
    "해설": "임대보증금 간주임대료 계산 시 차감하는 금융수익의 범위에는 수입이자, 할인료, 배당금만 포함되며, '유가증권처분이익'은 포함되지 않습니다."
  },
  {
    "id": "tax_so_4",
    "no": 4,
    "sector": "소득세",
    "내용": "4. 「소득세법」상 거주자의 부동산과 관련된 사업소득에 관한 설명으로 옳은 것은?",
    "옵션": [
      { "no": 1, "text": "국외에 소재하는 주택의 임대소득은 주택 수에 관계없이 과세하지 아니한다." },
      { "no": 2, "text": "공익사업을 위한 토지 등의 취득 및 보상에 관한 법률에 따른 공익사업과 관련하여 지역권을 대여함으로서 발생하는 소득은 부동산업에서 발생하는 소득으로 한다." },
      { "no": 3, "text": "부동산임대업에서 발생하는 사업소득의 납세지는 부동산 소재지로 한다." },
      { "no": 4, "text": "국내에 소재하는 논·밭을 작물 생산에 이용하게 함으로써 발생하는 사업소득은 소득세를 과세하지 아니한다." },
      { "no": 5, "text": "주거용 건물 임대업에서 발생한 결손금은 종합소득 과세표준을 계산할 때 공제하지 아니한다." }
    ],
    "answer": 4,
    "해설": "• 4번이 전통적인 비과세 규정에 부합하는 옳은 지문으로 정답입니다. 식량 생산 지원 목적을 위해 논·밭을 작물 생산처로 대여하고 얻는 소득은 전액 비과세합니다.\n• 1번: 국외주택 임대소득은 무조건 과세합니다.\n• 2번: 공익사업 관련 지역권 대여는 '기타소득'입니다.\n• 3번: 소득세법상 거주자의 납세지는 물건 소재지가 아니라 사람 기준인 '주소지'입니다.\n• 5번: 주거용 건물(주택) 임대업 결손금은 예외적으로 다른 종합소득에서 공제받을 수 있습니다."
  },
  {
    "id": "tax_so_5",
    "no": 5,
    "sector": "소득세",
    "내용": "5. 「소득세법」상 부동산임대업에서 발생한 소득에 관한 설명으로 틀린 것은?",
    "옵션": [
      { "no": 1, "text": "해당 과세기간의 주거용 건물 임대업을 제외한 부동산임대업에서 발생한 결손금은 그 과세기간의 종합소득과세표준을 계산할 때 공제하지 않는다." },
      { "no": 2, "text": "사업소득에 부동산임대업에서 발생한 소득이 포함되어 있는 사업자는 그 소득별로 구분하여 회계처리하여야 한다." },
      { "no": 3, "text": "3주택 이상을 소유한 거주자가 주택과 주택부수토지를 임대한 경우에는 법령으로 정하는 바에 따라 계산한 금액(간주임대료)을 총수입금액에 산입한다." },
      { "no": 4, "text": "간주임대료 계산 시 3주택 이상 여부 판정에 있어 주택 수에 포함되지 않는 주택이란 주거의 용도로만 쓰이는 면적이 1호 또는 1세대당 40m² 이하인 주택으로서 해당 과세기간의 기준시가가 2억원 이하인 주택을 말한다." },
      { "no": 5, "text": "해당 과세기간에 분리과세 주택임대소득이 있는 거주자는 그 종합소득 과세표준을 그 과세기간의 다음 연도 5월 1일부터 5월 31일까지 신고하여야 한다." }
    ],
    "answer": 3,
    "해설": "3주택 이상을 소유했다고 무조건 간주임대료를 산입하는 것이 아니라, 3주택 이상이면서 동시에 전세 보증금 등의 합계액이 '3억원을 초과'하는 요건까지 모두 충족해야 산입 대상이 됩니다."
  },
  {
    "id": "tax_so_6",
    "no": 6,
    "sector": "소득세",
    "내용": "6. 주택임대사업자인 거주자 甲의 국내주택 임대현황을 참고하여 계산한 주택임대에 따른 2026년 귀속 사업소득의 총수입금액은? (단, 이자율은 연 4%로 가정)<br><br><div style='border: 2px solid #475569; background-color: #ffffff; padding: 15px; margin: 10px 0; border-radius: 6px; font-family: sans-serif; white-space: pre-wrap; line-height: 1.8; font-weight: 500;'>• A주택(85m²) : 보증금 3억원 / 월세 50만원 / 기준시가 5억원\n• B주택(40m²) : 보증금 1억원 / 월세 없음 / 기준시가 2억원\n• C주택(109m²) : 보증금 5억원 / 월세 100만원 / 기준시가 7억원</div>",
    "옵션": [
      { "no": 1, "text": "0원" },
      { "no": 2, "text": "16,800,000원" },
      { "no": 3, "text": "18,000,000원" },
      { "no": 4, "text": "32,400,000원" },
      { "no": 5, "text": "54,000,000원" }
    ],
    "answer": 3,
    "해설": "• B주택은 40㎡ 이하이면서 기준시가 2억원 이하이므로 보증금 간주임대료 계산 시 주택 수 산정에서 자동으로 제외됩니다.\n• 따라서 甲은 A, C주택으로 구성된 2주택 소유자로 판단되어 전세 보증금에 대한 간주임대료를 계산하지 않습니다.\n• 최종 총수입금액은 순수 월세 수입인 (A주택 50만원 + C주택 100만원) × 12개월 = 1,800만원이 됩니다."
  },
  {
    "id": "tax_so_7",
    "no": 7,
    "sector": "소득세",
    "내용": "7. 다음은 거주자 甲이 소유하고 있는 상가건물 임대에 관한 자료이다. 부동산임대업의 사업소득을 장부에 기장하여 신고하는 경우 2026년도 부동산임대업의 총수입금액은? (단, 이자율 연 6% 가정)<br><br><div style='border: 2px solid #475569; background-color: #ffffff; padding: 15px; margin: 10px 0; border-radius: 6px; font-family: sans-serif; white-space: pre-wrap; line-height: 1.8; font-weight: 500;'>• 임대기간 : 2026.1.1. ~ 2026.12.31.\n• 계약내용 : 월임대료 1,000,000원 / 임대보증금 500,000,000원\n• 부동산가액 : 건물 취득가액 2억원 / 토지 취득가액 3억원\n• 보증금 운용수익 : 수입이자 1,000,000원 / 유가증권처분이익 2,000,000원</div>",
    "옵션": [
      { "no": 1, "text": "18,000,000원" },
      { "no": 2, "text": "29,000,000원" },
      { "no": 3, "text": "30,000,000원" },
      { "no": 4, "text": "39,000,000원" },
      { "no": 5, "text": "40,000,000원" }
    ],
    "answer": 2,
    "해설": "• 1년 총 임대료 = 100만원 × 12개월 = 1,200만원입니다.\n• 상가 간주임대료 = (보증금 5억원 - 건물 취득가액 2억원) × 6% - 금융수익(수입이자 100만원) = 1,700만원입니다. (※ 토지 취득가액과 유가증권처분이익은 산식 계산 및 금융수익 차감에서 제외)\n• 따라서 총수입금액은 임대료 1,200만원 + 간주임대료 1,700만원 = 2,900만원이 되므로 정답은 2번입니다."
  },
  {
    "id": "tax_so_8",
    "no": 8,
    "sector": "소득세",
    "내용": "8. 소득세법령상 거주자의 부동산과 관련된 사업소득에 관한 설명으로 옳은 것은?",
    "옵션": [
      { "no": 1, "text": "해당 과세기간의 종합소득금액이 있는 거주자는 그 종합소득 과세표준을 그 과세기간의 다음 연도 5월 1일부터 5월 31일까지 관할 세무서장에게 신고하여야 하며, 해당 과세기간에 분리과세 주택임대소득이 있는 경우에도 이를 적용한다." },
      { "no": 2, "text": "공장재단을 대여하는 사업은 부동산임대업에 해당되지 않는다." },
      { "no": 3, "text": "해당 과세기간의 주거용 건물 임대업을 제외한 부동산임대업에서 발생한 결손금은 그 과세기간의 종합소득 과세표준을 계산할 때 공제한다." },
      { "no": 4, "text": "「공익사업을 위한 토지 등의 취득 및 보상에 관한 법률」에 따른 공익사업과 관련하여 지역권을 설정함으로써 발생하는 소득은 부동산업에서 발생하는 소득에 해당한다." },
      { "no": 5, "text": "사업소득에 부동산임대업에서 발생한 소득이 포함되어 있는 사업자는 그 소득별로 구분하지 않고 회계처리하여야 한다." }
    ],
    "answer": 1,
    "해설": "• 1번이 확정신고 의무 규정에 완벽히 부합하는 옳은 지문으로 정답입니다.\n• 2번: 공장재단 및 광업재단을 대여하는 유상 행위도 부동산임대업(부동산업) 범위에 명확히 포함됩니다.\n• 3번: 주택(주거용)을 제외한 상가·토지 등의 임대업 결손금은 타 종합소득에서 공제할 수 없고 전액 이월결손금으로 묶어둡니다.\n• 4번: 공익사업 관련 지역권 설정·대여 소득은 '기타소득'입니다.\n• 5번: 부동산임대업 소득이 섞여 있는 사업자는 소득별로 명확하게 '구분'하여 주식 회계를 처리하여야 합니다."
  }
]